pykeen/__init__.py
pykeen/__main__.py
pykeen/cli.py
pykeen/constants.py
pykeen/inverse.py
pykeen/losses.py
pykeen/predict.py
pykeen/py.typed
pykeen/regularizers.py
pykeen/typing.py
pykeen/utils.py
pykeen/version.py
pykeen/ablation/__init__.py
pykeen/ablation/ablation.py
pykeen/checkpoints/__init__.py
pykeen/checkpoints/base.py
pykeen/checkpoints/inspection.py
pykeen/checkpoints/keeper.py
pykeen/checkpoints/schedule.py
pykeen/checkpoints/utils.py
pykeen/contrib/__init__.py
pykeen/contrib/lightning.py
pykeen/datasets/__init__.py
pykeen/datasets/__main__.py
pykeen/datasets/analysis.py
pykeen/datasets/aristo.py
pykeen/datasets/base.py
pykeen/datasets/biokg.py
pykeen/datasets/ckg.py
pykeen/datasets/cli.py
pykeen/datasets/codex.py
pykeen/datasets/conceptnet.py
pykeen/datasets/countries.py
pykeen/datasets/cskg.py
pykeen/datasets/db100k.py
pykeen/datasets/dbpedia.py
pykeen/datasets/drkg.py
pykeen/datasets/freebase.py
pykeen/datasets/generate.py
pykeen/datasets/globi.py
pykeen/datasets/hetionet.py
pykeen/datasets/literal_base.py
pykeen/datasets/mocks.py
pykeen/datasets/ogb.py
pykeen/datasets/openbiolink.py
pykeen/datasets/pharmebinet.py
pykeen/datasets/pharmkg.py
pykeen/datasets/primekg.py
pykeen/datasets/utils.py
pykeen/datasets/wd50k.py
pykeen/datasets/wikidata5m.py
pykeen/datasets/wordnet.py
pykeen/datasets/yago.py
pykeen/datasets/ea/__init__.py
pykeen/datasets/ea/base.py
pykeen/datasets/ea/combination.py
pykeen/datasets/ea/openea.py
pykeen/datasets/ea/wk3l.py
pykeen/datasets/inductive/__init__.py
pykeen/datasets/inductive/base.py
pykeen/datasets/inductive/ilp_teru.py
pykeen/datasets/inductive/ilpc2022.py
pykeen/datasets/kinships/__init__.py
pykeen/datasets/kinships/test.txt
pykeen/datasets/kinships/train.txt
pykeen/datasets/kinships/valid.txt
pykeen/datasets/nations/__init__.py
pykeen/datasets/nations/literals.txt
pykeen/datasets/nations/test.txt
pykeen/datasets/nations/train.txt
pykeen/datasets/nations/valid.txt
pykeen/datasets/umls/__init__.py
pykeen-1.11.1.dist-info/licenses/AUTHORS.md
pykeen-1.11.1.dist-info/licenses/LICENSE
pykeen-1.11.1.dist-info/METADATA
pykeen-1.11.1.dist-info/WHEEL
pykeen-1.11.1.dist-info/entry_points.txt
pykeen-1.11.1.dist-info/top_level.txt
pykeen-1.11.1.dist-info/RECORD
