Metadata-Version: 2.4
Name: pykeen
Version: 1.11.1
Summary: A package for training and evaluating multimodal knowledge graph embeddings
Author-email: Mehdi Ali <pykeen2019@gmail.com>, Max Berrendorf <max.berrendorf@gmail.com>, Laurent Vermue <pykeen2019@gmail.com>, Charles Tapley Hoyt <cthoyt@gmail.com>
Maintainer-email: Max Berrendorf <max.berrendorf@gmail.com>, Charles Tapley Hoyt <cthoyt@gmail.com>
License: MIT License
Project-URL: Bug Tracker, https://github.com/pykeen/pykeen/issues
Project-URL: Homepage, https://github.com/pykeen/pykeen
Project-URL: Repository, https://github.com/pykeen/pykeen.git
Project-URL: Documentation, https://pykeen.readthedocs.io
Keywords: snekpack,cookiecutter,Knowledge Graph Embeddings,Machine Learning,Data Mining,Linked Data
Classifier: Development Status :: 5 - Production/Stable
Classifier: Environment :: Console
Classifier: Intended Audience :: Science/Research
Classifier: License :: OSI Approved :: MIT License
Classifier: Operating System :: OS Independent
Classifier: Framework :: Pytest
Classifier: Framework :: tox
Classifier: Framework :: Sphinx
Classifier: Programming Language :: Python
Classifier: Programming Language :: Python :: 3.10
Classifier: Programming Language :: Python :: 3.11
Classifier: Programming Language :: Python :: 3.12
Classifier: Programming Language :: Python :: 3 :: Only
Classifier: Topic :: Scientific/Engineering :: Artificial Intelligence
Classifier: Topic :: Scientific/Engineering :: Chemistry
Classifier: Topic :: Scientific/Engineering :: Bio-Informatics
Classifier: Topic :: Scientific/Engineering :: Mathematics
Classifier: Topic :: Scientific/Engineering :: Information Analysis
Requires-Python: >=3.10
License-File: LICENSE
License-File: AUTHORS.md
Requires-Dist: dataclasses-json
Requires-Dist: numpy
Requires-Dist: numpy
Requires-Dist: scipy>=1.7.0
Requires-Dist: click
Requires-Dist: click_default_group
Requires-Dist: scikit-learn
Requires-Dist: torch>=2.0
Requires-Dist: tqdm
Requires-Dist: requests
Requires-Dist: optuna>=2.0.0
Requires-Dist: pandas>=1.0.0
Requires-Dist: tabulate
Requires-Dist: more_click
Requires-Dist: more_itertools
Requires-Dist: pystow>=0.4.3
Requires-Dist: docdata>=0.0.5
Requires-Dist: class_resolver>=0.6.0
Requires-Dist: pyyaml
Requires-Dist: torch_max_mem>=0.1.4
Requires-Dist: torch-ppr>=0.0.7
Requires-Dist: typing_extensions
Provides-Extra: templating
Requires-Dist: jinja2; extra == "templating"
Provides-Extra: plotting
Requires-Dist: matplotlib; extra == "plotting"
Requires-Dist: seaborn; extra == "plotting"
Provides-Extra: wordcloud
Requires-Dist: wordcloud; extra == "wordcloud"
Requires-Dist: IPython; extra == "wordcloud"
Provides-Extra: opt-einsum
Requires-Dist: opt_einsum; extra == "opt-einsum"
Provides-Extra: mlflow
Requires-Dist: mlflow>=1.8.0; extra == "mlflow"
Provides-Extra: ogb
Requires-Dist: ogb>=1.3.4; extra == "ogb"
Provides-Extra: wandb
Requires-Dist: wandb; extra == "wandb"
Provides-Extra: neptune
Requires-Dist: neptune-client; extra == "neptune"
Provides-Extra: tensorboard
Requires-Dist: tensorboard; extra == "tensorboard"
Provides-Extra: transformers
Requires-Dist: transformers; extra == "transformers"
Provides-Extra: lightning
Requires-Dist: pytorch_lightning>=1.7.2; extra == "lightning"
Provides-Extra: biomedicine
Requires-Dist: bioregistry; extra == "biomedicine"
Requires-Dist: pyobo>=0.8.7; extra == "biomedicine"
Provides-Extra: tests
Requires-Dist: unittest-templates>=0.0.5; extra == "tests"
Requires-Dist: coverage; extra == "tests"
Requires-Dist: pytest; extra == "tests"
Provides-Extra: docs
Requires-Dist: sphinx>=8.0; extra == "docs"
Requires-Dist: sphinx-rtd-theme>=3.0; extra == "docs"
Requires-Dist: sphinx-click; extra == "docs"
Requires-Dist: sphinx_automodapi; extra == "docs"
Requires-Dist: texext; extra == "docs"
Requires-Dist: graphviz; extra == "docs"
Provides-Extra: pyg
Requires-Dist: torch_geometric; extra == "pyg"
Dynamic: license-file
